{"1":{"commands":null,"graph_data":{"height":161,"initial_node":false,"node_name":"57524229","width":250.000366,"x":-1226.06189,"y":-93.781433},"next":null,"text":"Фрррр","type":"dialog"},"10":{"commands":null,"graph_data":{"height":181.999939,"initial_node":false,"node_name":"57537525","width":259.999603,"x":-32.062103,"y":-188.781433},"next":"11","text":"Ах, какие прекрасные слова\nДа он романтик","type":"dialog"},"11":{"commands":["set lovers_asking_what_she_like false","set lovers_she_has_been_asked_about_what_she_like True"],"graph_data":{"height":231,"initial_node":false,"node_name":"55447109","width":471.000153,"x":267.937836,"y":-188.781433},"next":null,"text":"Хихик","type":"dialog"},"12":{"commands":null,"graph_data":{"height":201,"initial_node":false,"node_name":"57582933","width":250.000244,"x":1077.937744,"y":143.218506},"next":"13","text":"Ваааау, какой он деловой\nи перспективный кись","type":"dialog"},"13":{"commands":["set lovers_asking_to_tell_about_him false","set lovers_she_has_been_told_about_him True"],"graph_data":{"height":236,"initial_node":false,"node_name":"55449605","width":369,"x":1407.937744,"y":143.218506},"next":null,"text":"Мне нравятся такие","type":"dialog"},"14":{"commands":null,"graph_data":{"height":406,"initial_node":false,"node_name":"57534597","width":429.000214,"x":507.937775,"y":773.218384},"responses":[{"conditions":null,"next":"15","text":"Рассказал он..."}],"text":"\"Однажды, я приготовил много-много сосисочек,\nи раздал их все детишкам. Потому что для меня\nнет большей награды, чем детская улыбка\"","type":"response"},"15":{"commands":null,"graph_data":{"height":161,"initial_node":false,"node_name":"57531525","width":278,"x":1077.937744,"y":773.218384},"next":"16","text":"Ах, какой он добрый и хороший","type":"dialog"},"16":{"commands":["set lovers_asking_to_tell_a_story false","set lovers_she_has_been_told_a_story True"],"graph_data":{"height":231,"initial_node":false,"node_name":"57849109","width":360,"x":1497.937744,"y":773.218384},"next":null,"text":"Вот все бы такими были как он!","type":"dialog"},"17":{"conditions":[{"condition":"lovers_she_has_been_told_about_him","condition_value_type":1,"sign":"=","value":true},{"condition":"lovers_she_has_been_told_a_story","condition_value_type":1,"sign":"=","value":true},{"condition":"lovers_she_has_been_asked_about_what_she_like","condition_value_type":1,"sign":"=","value":true}],"false":"19","graph_data":{"height":368,"initial_node":false,"node_name":"57639445","width":447.000214,"x":488.937775,"y":1424.218262},"true":"18","type":"condition"},"18":{"commands":["set lovers_girl_said_yes True"],"graph_data":{"height":282,"initial_node":false,"node_name":"57534981","width":353,"x":1028.937744,"y":1204.218262},"next":null,"text":"Знаешь, кажется я нашла того самого!\nЯ никому не отдам такого прекрасного\nкотика как он. Спасибо, что помогла\nоткрыть глаза!","type":"dialog"},"19":{"commands":null,"graph_data":{"height":161,"initial_node":false,"node_name":"57634725","width":297,"x":1028.937744,"y":1564.218262},"next":null,"text":"Кажется он что-то хочет сказать","type":"dialog"},"2":{"conditions":[{"condition":"lovers_asking_to_tell_about_him","condition_value_type":1,"sign":"=","value":true}],"false":"3","graph_data":{"height":212,"initial_node":false,"node_name":"57367445","width":333.000031,"x":-452.062042,"y":251.218506},"true":"20","type":"condition"},"20":{"commands":null,"graph_data":{"height":236,"initial_node":false,"node_name":"36758629","width":391.000122,"x":57.937866,"y":173.218506},"next":"21","text":"\"У меня большие планы на жизь. Я мечтаю\nо большой семье в большом домике, который\nв скором времени планирую построить...","type":"dialog"},"21":{"commands":null,"graph_data":{"height":406,"initial_node":false,"node_name":"55484005","width":383.000244,"x":567.937744,"y":143.218506},"responses":[{"conditions":null,"next":"12","text":"Сказал он..."}],"text":"А пока, я увлекаюсь высокой кухней\nи коплю силы для дальнейших свершений.\nТак что я весь в твоём распоряжении\"","type":"response"},"3":{"conditions":[{"condition":"lovers_asking_to_tell_a_story","condition_value_type":1,"sign":"=","value":true}],"false":"17","graph_data":{"height":212,"initial_node":false,"node_name":"57336885","width":318.000122,"x":108.937866,"y":1084.218262},"true":"14","type":"condition"},"4":{"conditions":[{"condition":"lovers_help_offered","condition_value_type":1,"sign":"=","value":true}],"false":"6","graph_data":{"height":212,"initial_node":false,"node_name":"57381381","width":272.999878,"x":-1306.06189,"y":146.218506},"true":"5","type":"condition"},"5":{"conditions":[{"condition":"lovers_asking_what_she_like","condition_value_type":1,"sign":"=","value":true}],"false":"2","graph_data":{"height":212,"initial_node":false,"node_name":"57558389","width":316,"x":-866.062012,"y":-133.781433},"true":"9","type":"condition"},"6":{"commands":null,"graph_data":{"height":166,"initial_node":false,"node_name":"57399445","width":250.000122,"x":-972.06189,"y":951.218384},"next":"7","text":"Мне сегодня так везёт","type":"dialog"},"7":{"commands":null,"graph_data":{"height":217,"initial_node":false,"node_name":"57396085","width":250,"x":-662.062012,"y":923.218384},"next":"8","text":"Только посмотри какой\nкрасивый котик пригласил\nменя на свидание","type":"dialog"},"8":{"commands":null,"graph_data":{"height":201,"initial_node":false,"node_name":"57442645","width":253.000061,"x":-332.062073,"y":923.218384},"next":null,"text":"Только он застенчивый\nкакой-то...","type":"dialog"},"9":{"commands":null,"graph_data":{"height":406.000122,"initial_node":false,"node_name":"57383205","width":401.000031,"x":-472.062042,"y":-448.781372},"responses":[{"conditions":null,"next":"10","text":"Он так сказал..."}],"text":"\"Когда я смотрю в твои прекрасные глазки,\nя чувствую себя, словно тысячи сосисочек\nупали на самого голодного котика в мире\"","type":"response"},"Initial":{"conditions":[{"condition":"lovers_girl_said_yes","condition_value_type":1,"sign":"=","value":true}],"false":"4","graph_data":{"height":212,"initial_node":true,"node_name":"57571509","width":292,"x":-1646.061768,"y":26.218506},"true":"1","type":"condition"},"connections":[{"from":"57571509","from_port":0,"to":"57524229","to_port":0},{"from":"57558389","from_port":1,"to":"57367445","to_port":0},{"from":"57367445","from_port":1,"to":"57336885","to_port":0},{"from":"57571509","from_port":1,"to":"57381381","to_port":0},{"from":"57381381","from_port":0,"to":"57558389","to_port":0},{"from":"57381381","from_port":1,"to":"57399445","to_port":0},{"from":"57399445","from_port":0,"to":"57396085","to_port":0},{"from":"57396085","from_port":0,"to":"57442645","to_port":0},{"from":"57558389","from_port":0,"to":"57383205","to_port":0},{"from":"57383205","from_port":0,"to":"57537525","to_port":0},{"from":"57537525","from_port":0,"to":"55447109","to_port":0},{"from":"55484005","from_port":0,"to":"57582933","to_port":0},{"from":"57582933","from_port":0,"to":"55449605","to_port":0},{"from":"57336885","from_port":0,"to":"57534597","to_port":0},{"from":"57534597","from_port":0,"to":"57531525","to_port":0},{"from":"57531525","from_port":0,"to":"57849109","to_port":0},{"from":"57336885","from_port":1,"to":"57639445","to_port":0},{"from":"57639445","from_port":0,"to":"57534981","to_port":0},{"from":"57639445","from_port":1,"to":"57634725","to_port":0},{"from":"57367445","from_port":0,"to":"36758629","to_port":0},{"from":"36758629","from_port":0,"to":"55484005","to_port":0}]}