{"1":{"commands":null,"graph_data":{"height":166,"initial_node":false,"node_name":"14388373","width":250.000183,"x":-804.445984,"y":588.276733},"next":"3","text":"Кхем-кхем...","type":"dialog"},"2":{"commands":null,"graph_data":{"height":236.000076,"initial_node":false,"node_name":"5940085","width":444.000183,"x":-846.445984,"y":129.276779},"next":null,"text":"Тебе придется добиться признания\nместных жителей, чтобы получить\nмногие из этих вещей","type":"dialog"},"3":{"commands":null,"graph_data":{"height":166,"initial_node":false,"node_name":"36230501","width":271.000244,"x":-444.446045,"y":588.276733},"next":"4","text":"Так и быть,  я помогу тебе","type":"dialog"},"4":{"commands":null,"graph_data":{"height":236,"initial_node":false,"node_name":"16701493","width":397.000244,"x":-84.446045,"y":588.276733},"next":"6","text":"Однако, перед этим тебе придется \nсобрать здесь некоторые киселячьи\nартифакты!","type":"dialog"},"5":{"commands":null,"graph_data":{"height":201,"initial_node":false,"node_name":"36070453","width":340.999878,"x":1295.553833,"y":588.276733},"next":"8","text":"Возможно если ты поможешь местным\nкотикам, они и тебе смогут помочь","type":"dialog"},"6":{"commands":null,"graph_data":{"height":201,"initial_node":false,"node_name":"35917813","width":354.999878,"x":395.553833,"y":588.276733},"next":"7","text":"Один из таких ты уже нашла,\nраз смогла попасть сюда","type":"dialog"},"7":{"commands":null,"graph_data":{"height":236,"initial_node":false,"node_name":"33776357","width":398.999878,"x":815.553833,"y":588.276733},"next":"5","text":"Но с другими это будет не так просто\nсделать, так как многие из них находятся\nв укромных уголках этого мира","type":"dialog"},"8":{"commands":["emmit show_activate_pillars_cutscene","set did_mystic_dweller_activate_pillars true"],"graph_data":{"height":236,"initial_node":false,"node_name":"14847509","width":472.999878,"x":1715.553833,"y":588.276733},"next":null,"text":"И помни, я слежу за тобой... хе-хе-хе...","type":"dialog"},"Initial":{"conditions":[{"condition":"did_mystic_dweller_activate_pillars","condition_value_type":1,"sign":"=","value":true}],"false":"1","graph_data":{"height":212,"initial_node":true,"node_name":"5841589","width":386.000122,"x":-1356.445923,"y":309.276764},"true":"2","type":"condition"},"connections":[{"from":"5841589","from_port":1,"to":"14388373","to_port":0},{"from":"5841589","from_port":0,"to":"5940085","to_port":0},{"from":"14388373","from_port":0,"to":"36230501","to_port":0},{"from":"36230501","from_port":0,"to":"16701493","to_port":0},{"from":"33776357","from_port":0,"to":"36070453","to_port":0},{"from":"16701493","from_port":0,"to":"35917813","to_port":0},{"from":"35917813","from_port":0,"to":"33776357","to_port":0},{"from":"36070453","from_port":0,"to":"14847509","to_port":0}]}